Workbook

Sheet Sheet3
A3: 合計 / 割引後売上 | B3: 列ラベル
A4: 行ラベル | B4: PC | C4: ディスプレイ | D4: 周辺機器 | E4: 総計
A5: 西日本 | B5: 73600 | D5: 18400 | E5: 92000
A6: 中部 | B6: 77600 | C6: 29100 | D6: 5820 | E6: 112520
A7: 東日本 | B7: 152000 | C7: 57000 | D7: 21850 | E7: 230850
A8: 総計 | B8: 303200 | C8: 86100 | D8: 46070 | E8: 435370

Sheet orders_data
A1: 注文ID | B1: 注文日 | C1: 商品名 | D1: 地域 | E1: 数量 | F1: カテゴリ | G1: 単価 | H1: 売上 | I1: 地域割引率 | J1: 割引後売上 | K1: 税込売上
A2: ORD-001 | B2: 2026/04/01 | C2: ノートPC | D2: 東日本 | E2: 2 | F2: =VLOOKUP(C2,product_master!$A$2:$C$5,2,FALSE) -> PC | G2: =VLOOKUP(C2,product_master!$A$2:$C$5,3,FALSE) -> 80000 | H2: =E2*G2 -> 160000 | I2: =VLOOKUP(D2,region_master!$A$2:$B$4,2,FALSE) -> 0.05 | J2: =H2*(1-I2) -> 152000 | K2: =J2*(1+controls!$B$2) -> 167200 | L2: q017 東日本かつPCの割引後売上合計 | M2: =SUMIFS(J2:J11,D2:D11,"東日本",F2:F11,"PC") -> 152000
A3: ORD-002 | B3: 2026/04/01 | C3: マウス | D3: 西日本 | E3: 5 | F3: =VLOOKUP(C3,product_master!$A$2:$C$5,2,FALSE) -> 周辺機器 | G3: =VLOOKUP(C3,product_master!$A$2:$C$5,3,FALSE) -> 2000 | H3: =E3*G3 -> 10000 | I3: =VLOOKUP(D3,region_master!$A$2:$B$4,2,FALSE) -> 0.08 | J3: =H3*(1-I3) -> 9200 | K3: =J3*(1+controls!$B$2) -> 10120 | L3: q018 西日本かつ周辺機器の件数 | M3: =COUNTIFS(D2:D11,"西日本",F2:F11,"周辺機器") -> 2
A4: ORD-003 | B4: 2026/04/02 | C4: キーボード | D4: 東日本 | E4: 3 | F4: =VLOOKUP(C4,product_master!$A$2:$C$5,2,FALSE) -> 周辺機器 | G4: =VLOOKUP(C4,product_master!$A$2:$C$5,3,FALSE) -> 5000 | H4: =E4*G4 -> 15000 | I4: =VLOOKUP(D4,region_master!$A$2:$B$4,2,FALSE) -> 0.05 | J4: =H4*(1-I4) -> 14250 | K4: =J4*(1+controls!$B$2) -> 15675 | L4: q019 PCの税込売上平均 | M4: =AVERAGEIF(F2:F11,"PC",K2:K11) -> 111173.33
A5: ORD-004 | B5: 2026/04/02 | C5: モニター | D5: 中部 | E5: 1 | F5: =VLOOKUP(C5,product_master!$A$2:$C$5,2,FALSE) -> ディスプレイ | G5: =VLOOKUP(C5,product_master!$A$2:$C$5,3,FALSE) -> 30000 | H5: =E5*G5 -> 30000 | I5: =VLOOKUP(D5,region_master!$A$2:$B$4,2,FALSE) -> 0.03 | J5: =H5*(1-I5) -> 29100 | K5: =J5*(1+controls!$B$2) -> 32010
A6: ORD-005 | B6: 2026/04/03 | C6: ノートPC | D6: 西日本 | E6: 1 | F6: =VLOOKUP(C6,product_master!$A$2:$C$5,2,FALSE) -> PC | G6: =VLOOKUP(C6,product_master!$A$2:$C$5,3,FALSE) -> 80000 | H6: =E6*G6 -> 80000 | I6: =VLOOKUP(D6,region_master!$A$2:$B$4,2,FALSE) -> 0.08 | J6: =H6*(1-I6) -> 73600 | K6: =J6*(1+controls!$B$2) -> 80960
A7: ORD-006 | B7: 2026/04/03 | C7: マウス | D7: 東日本 | E7: 4 | F7: =VLOOKUP(C7,product_master!$A$2:$C$5,2,FALSE) -> 周辺機器 | G7: =VLOOKUP(C7,product_master!$A$2:$C$5,3,FALSE) -> 2000 | H7: =E7*G7 -> 8000 | I7: =VLOOKUP(D7,region_master!$A$2:$B$4,2,FALSE) -> 0.05 | J7: =H7*(1-I7) -> 7600 | K7: =J7*(1+controls!$B$2) -> 8360
A8: ORD-007 | B8: 2026/04/04 | C8: モニター | D8: 東日本 | E8: 2 | F8: =VLOOKUP(C8,product_master!$A$2:$C$5,2,FALSE) -> ディスプレイ | G8: =VLOOKUP(C8,product_master!$A$2:$C$5,3,FALSE) -> 30000 | H8: =E8*G8 -> 60000 | I8: =VLOOKUP(D8,region_master!$A$2:$B$4,2,FALSE) -> 0.05 | J8: =H8*(1-I8) -> 57000 | K8: =J8*(1+controls!$B$2) -> 62700
A9: ORD-008 | B9: 2026/04/04 | C9: キーボード | D9: 西日本 | E9: 2 | F9: =VLOOKUP(C9,product_master!$A$2:$C$5,2,FALSE) -> 周辺機器 | G9: =VLOOKUP(C9,product_master!$A$2:$C$5,3,FALSE) -> 5000 | H9: =E9*G9 -> 10000 | I9: =VLOOKUP(D9,region_master!$A$2:$B$4,2,FALSE) -> 0.08 | J9: =H9*(1-I9) -> 9200 | K9: =J9*(1+controls!$B$2) -> 10120
A10: ORD-009 | B10: 2026/04/05 | C10: ノートPC | D10: 中部 | E10: 1 | F10: =VLOOKUP(C10,product_master!$A$2:$C$5,2,FALSE) -> PC | G10: =VLOOKUP(C10,product_master!$A$2:$C$5,3,FALSE) -> 80000 | H10: =E10*G10 -> 80000 | I10: =VLOOKUP(D10,region_master!$A$2:$B$4,2,FALSE) -> 0.03 | J10: =H10*(1-I10) -> 77600 | K10: =J10*(1+controls!$B$2) -> 85360
A11: ORD-010 | B11: 2026/04/05 | C11: マウス | D11: 中部 | E11: 3 | F11: =VLOOKUP(C11,product_master!$A$2:$C$5,2,FALSE) -> 周辺機器 | G11: =VLOOKUP(C11,product_master!$A$2:$C$5,3,FALSE) -> 2000 | H11: =E11*G11 -> 6000 | I11: =VLOOKUP(D11,region_master!$A$2:$B$4,2,FALSE) -> 0.03 | J11: =H11*(1-I11) -> 5820 | K11: =J11*(1+controls!$B$2) -> 6402
A14: ▼ 学習用アウトプット欄（ここに数式や結果を入れてください）

Sheet product_master
A1: 商品名 | B1: カテゴリ | C1: 単価
A2: ノートPC | B2: PC | C2: 80000
A3: マウス | B3: 周辺機器 | C3: 2000
A4: キーボード | B4: 周辺機器 | C4: 5000
A5: モニター | B5: ディスプレイ | C5: 30000

Sheet region_master
A1: 地域 | B1: 割引率
A2: 東日本 | B2: 0.05
A3: 西日本 | B3: 0.08
A4: 中部 | B4: 0.03

Sheet controls
A1: コントロール
A2: 消費税率 | B2: 0.1
A4: ※ q016 では controls!$B$2 を絶対参照で使います。

Sheet pivot_task
A1: q020 ピボット導入
A2: orders_data を元にピボットテーブルを作成してください。
A3: 行：地域
A4: 列：カテゴリ
A5: 値：割引後売上（合計）
A6: 作成したピボット表を見て、下の青セルに結果を転記してください。
A8: 転記欄
A9: 東日本 × PC | B9: 152000
A10: 西日本 × 周辺機器 | B10: 18400
A11: 中部 × PC | B11: 77600
A12: 総計 | B12: 435370

Sheet practice
A1: ID | B1: やること | C1: 入力場所 | D1: あなたの結果 | E1: 期待値 | F1: 判定
A2: q011 | B2: product_masterを参照してカテゴリを埋める（VLOOKUP） | C2: orders_data!F2:F11 | D2: =COUNTA(orders_data!F2:F11) -> 10 | E2: =COUNTA(orders_data!C2:C11) -> 10 | F2: =IF(D2="","未入力",IF(D2=E2,"OK","NG")) -> OK
A3: q012 | B3: product_masterを参照して単価を埋める（VLOOKUP） | C3: orders_data!G2:G11 | D3: =SUM(orders_data!G2:G11) -> 316000 | E3: =SUMPRODUCT(COUNTIF(orders_data!C2:C11,product_master!A2:A5),product_master!C2:C5) -> 316000 | F3: =IF(D3="","未入力",IF(ABS(D3-E3)<0.0001,"OK","NG")) -> OK
A4: q013 | B4: 売上 = 数量×単価 を計算 | C4: orders_data!H2:H11 | D4: =SUM(orders_data!H2:H11) -> 459000 | E4: =SUMPRODUCT(orders_data!E2:E11,orders_data!G2:G11) -> 459000 | F4: =IF(D4="","未入力",IF(ABS(D4-E4)<0.0001,"OK","NG")) -> OK
A5: q014 | B5: region_masterを参照して地域割引率を埋める（VLOOKUP） | C5: orders_data!I2:I11 | D5: =SUM(orders_data!I2:I11) -> 0.53 | E5: =SUMPRODUCT(COUNTIF(orders_data!D2:D11,region_master!A2:A4),region_master!B2:B4) -> 0.53 | F5: =IF(D5="","未入力",IF(ABS(D5-E5)<0.0001,"OK","NG")) -> OK
A6: q015 | B6: 割引後売上 = 売上×(1-地域割引率) | C6: orders_data!J2:J11 | D6: =SUM(orders_data!J2:J11) -> 435370 | E6: =SUMPRODUCT(orders_data!H2:H11,(1-orders_data!I2:I11)) -> 435370 | F6: =IF(D6="","未入力",IF(ABS(D6-E6)<0.0001,"OK","NG")) -> OK
A7: q016 | B7: 税込売上 = 割引後売上×(1+controls!$B$2) | C7: orders_data!K2:K11 | D7: =SUM(orders_data!K2:K11) -> 478907 | E7: =SUMPRODUCT(orders_data!J2:J11)*(1+controls!$B$2) -> 478907 | F7: =IF(D7="","未入力",IF(ABS(D7-E7)<0.0001,"OK","NG")) -> OK
A8: q017 | B8: 東日本かつPCの割引後売上合計（SUMIFS） | C8: orders_data!M2 | D8: =orders_data!M2 -> 152000 | E8: =SUMIFS(orders_data!J2:J11,orders_data!D2:D11,"東日本",orders_data!F2:F11,"PC") -> 152000 | F8: =IF(D8="","未入力",IF(ABS(D8-E8)<0.0001,"OK","NG")) -> OK
A9: q018 | B9: 西日本かつ周辺機器の件数（COUNTIFS） | C9: orders_data!M3 | D9: =orders_data!M3 -> 2 | E9: =COUNTIFS(orders_data!D2:D11,"西日本",orders_data!F2:F11,"周辺機器") -> 2 | F9: =IF(D9="","未入力",IF(D9=E9,"OK","NG")) -> OK
A10: q019 | B10: PCの税込売上平均（AVERAGEIF） | C10: orders_data!M4 | D10: =orders_data!M4 -> 111173.33 | E10: =AVERAGEIF(orders_data!F2:F11,"PC",orders_data!K2:K11) -> 111173.33 | F10: =IF(D10="","未入力",IF(ABS(D10-E10)<0.0001,"OK","NG")) -> OK
A11: q020 | B11: ピボットを作成し、pivot_taskのB9:B12に結果転記 | C11: pivot_task!B9:B12 | D11: =SUM(pivot_task!B9:B12) -> 683370 | E11: =SUM(SUMIFS(orders_data!J2:J11,orders_data!D2:D11,"東日本",orders_data!F2:F11,"PC"),SUMIFS(orders_data!J2:J11,orders_data!D2:D11,"西日本",orders_data!F2:F11,"周辺機器"),SUMIFS(orders_data!J2:J11,orders_data!D2:D11,"中部",orders_data!F2:F11,"PC"),SUM(orders_data!J2:J11)) -> 683370 | F11: =IF(D11="","未入力",IF(ABS(D11-E11)<0.0001,"OK","NG")) -> OK

Sheet README
A1: このExcelは、q011〜q020を「実際に手を動かして」学べる続編ワークブックです。
A3: 【使い方】
A4: 1) orders_data シートの青文字セルに数式を入力します。
A5: 2) q020 は、orders_data を元に自分でピボットテーブルを作ります。
A6: 3) ピボットの結果を pivot_task シートに転記します。
A7: 4) practice シートで OK / NG を確認します。
A9: 【この回で身につけること】
A10: - VLOOKUP による参照
A11: - 絶対参照（controls!$B$2）
A12: - SUMIFS / COUNTIFS / AVERAGEIF
A13: - ピボットテーブルの初歩
